collection_views/__init__.py
collection_views/_immutable_view_list.py
collection_views/py.typed
collection_views-0.0.2.dist-info/LICENSE
collection_views-0.0.2.dist-info/METADATA
collection_views-0.0.2.dist-info/WHEEL
collection_views-0.0.2.dist-info/RECORD
